README.md
setup.py
cmdc/__init__.py
cmdc/client.py
cmdc/examples.py
cmdc/utils.py
cmdc.egg-info/PKG-INFO
cmdc.egg-info/SOURCES.txt
cmdc.egg-info/dependency_links.txt
cmdc.egg-info/requires.txt
cmdc.egg-info/top_level.txt