Metadata-Version: 2.1
Name: cmdc
Version: 0.2.0
Summary: Python client for accessing the COVID Modeling Data Collaborative database
Home-page: https://github.com/valorumdata/cmdc
Author: Valorum Data
Author-email: info@valorumdata.com
License: UNKNOWN
Project-URL: Bug Reports, https://github.com/valorumdata/cmdc.py/issues
Project-URL: Source, https://github.com/valorumdata/cmdc.py
Platform: UNKNOWN
Classifier: Development Status :: 3 - Alpha
Classifier: Intended Audience :: Developers
Classifier: Topic :: Software Development :: Build Tools
Classifier: License :: OSI Approved :: MIT License
Classifier: Programming Language :: Python :: 3
Classifier: Programming Language :: Python :: 3.5
Classifier: Programming Language :: Python :: 3.6
Classifier: Programming Language :: Python :: 3.7
Classifier: Programming Language :: Python :: 3.8
Classifier: Programming Language :: Python :: 3 :: Only
Requires-Python: >=3.5, <4
